{"cameraMode":{"drawMode":0,"name":"Shaded","section":"Shading Mode"},"sceneLighting":true,"audioPlay":false,"sceneViewState":{"m_AlwaysRefresh":false,"showFog":true,"showSkybox":true,"showFlares":true,"showImageEffects":true,"showParticleSystems":true,"showVisualEffectGraphs":true,"m_FxEnabled":true},"in2DMode":false,"pivot":{"x":18.39936637878418,"y":5.4783172607421879,"z":-6.42167854309082},"rotation":{"x":-0.029643598943948747,"y":0.3648057281970978,"z":0.01148642972111702,"w":0.9307217001914978},"size":13.59500789642334,"orthographic":false}